virtumouse.py
virtumouse-0.0.1.dist-info/METADATA
virtumouse-0.0.1.dist-info/WHEEL
virtumouse-0.0.1.dist-info/entry_points.txt
virtumouse-0.0.1.dist-info/top_level.txt
virtumouse-0.0.1.dist-info/RECORD
