Metadata-Version: 2.1
Name: virtumouse
Version: 0.0.1
Summary: virtumouse is a virtual mouse using a finger with a camera.
Home-page: https://github.com/kumanekosub/virtumouse
Author: KO KUMADA
Author-email: s2122023@stu.musashino-u.ac.jp
License: UNKNOWN
Project-URL: Bug Tracker, https://github.com/kumanekosub/virtumouse
Platform: UNKNOWN
Classifier: Programming Language :: Python :: 3
Classifier: License :: OSI Approved :: MIT License
Classifier: Operating System :: OS Independent
Requires-Python: >=3.8
